{
	"spider": "https://github.tbedu.top/https://raw.githubusercontent.com/hoheiya9527/TvboxSelf/main/spider_backup/fan_250621;md5;9b4406d5c1de4d695db13d5f771a835a",
	"wallpaper": "http://www.kf666888.cn/api/tvbox/img",
	"lives": [{
		"name": "直播",
		"type": 0,
		"url": "https://iptv.catvod.com/tv.m3u",
		"playerType": 1,
		"ua": "okhttp/3.12.13",
		"epg": "http://epg.51zmt.top:8000/api/diyp/?ch={name}&date={date}",
		"logo": "https://live.fanmingming.com/tv/{name}.png"
	}],
	"remove_string": "公众号|神秘的哥哥们|叨观荐影|WX|微信|分享",
	"filter": "饭|4K|臻彩",
	"sites": [{
		"key": "豆豆",
		"name": "豆瓣推荐",
		"type": 3,
		"api": "csp_DouDouGuard",
		"searchable": 0,
		"quickSearch": 1,
		"filterable": 0
	},
	{
		"key": "文采",
		"name": "解析-极影",
		"type": 3,
		"api": "csp_JpysGuard",
		"timeout": 10,
		"playerType": 1,
		"searchable": 1,
		"quickSearch": 1,
		"changeable": 1
	},
	{
		"key": "比特",
		"name": "解析-比特",
		"type": 3,
		"api": "csp_BttwooGuard",
		"timeout": 10,
		"searchable": 1,
		"quickSearch": 1,
		"changeable": 1
	},
	{
		"key": "玩偶",
		"name": "云盘-玩偶",
		"type": 3,
		"api": "csp_WoGGGuard",
		"timeout": 30,
		"searchable": 1,
		"quickSearch": 1,
		"changeable": 0,
		"ext": {
			"Cloud-drive": "tvfan/Cloud-drive.txt",
			"from": "4k|auto",
			"siteUrl": "https://www.wogg.com/",
			"danMu": "弹"
		}
	},
	{
		"key": "UC",
		"name": "云盘-UC",
		"type": 3,
		"api": "csp_UuSsGuard",
		"searchable": 1,
		"quickSearch": 1,
		"changeable": 0,
		"ext": {
			"Cloud-drive": "tvfan/Cloud-drive.txt",
			"from": "auto|4k"
		}
	},
	{
		"key": "白白",
		"name": "解析-白白",
		"type": 3,
		"api": "csp_SbaibaiGuard",
		"timeout": 10,
		"playerType": 1,
		"searchable": 1,
		"quickSearch": 1,
		"changeable": 1
	},
	{
		"key": "苹果",
		"name": "解析-苹果",
		"type": 3,
		"api": "csp_LiteAppleGuard",
		"timeout": 10,
		"searchable": 1,
		"quickSearch": 1,
		"changeable": 1
	},
	{
		"key": "荐片",
		"name": "解析-荐片",
		"type": 3,
		"api": "csp_JPJGuard",
		"timeout": 10,
		"playerType": 1,
		"searchable": 1,
		"quickSearch": 1,
		"changeable": 0
	}]
}